{
	"id": "6b865b69-51ba-4b85-81ae-c84b1f5cdcf9",
	"name": "New Collection",
	"timestamp": "2023-04-12T01:37:09.702Z",
	"collection_id": "26799808-009874e4-b9e8-483e-9134-ce82310a66ac",
	"folder_id": 0,
	"environment_id": "0",
	"totalPass": 0,
	"delay": 0,
	"persist": true,
	"status": "finished",
	"startedAt": "2023-04-12T01:32:45.629Z",
	"totalFail": 0,
	"results": [
		{
			"id": "00c8ab54-2434-4472-83a9-6fb6e81957ec",
			"name": "api starwars localhost",
			"url": "http://127.0.0.1:5000/search?field=planets&query=dagobah",
			"time": 4,
			"responseCode": {
				"code": 200,
				"name": "OK"
			},
			"tests": {},
			"testPassFailCounts": {},
			"times": [
				3737,
				1723,
				2138,
				1174,
				1154,
				1085,
				1252,
				1209,
				1211,
				1220,
				16986,
				1216,
				1112,
				1220,
				1111,
				1214,
				1212,
				1323,
				1214,
				1223,
				1131,
				1085,
				3471,
				1830,
				1574,
				1475,
				1729,
				1825,
				7,
				1194,
				1116,
				1209,
				1329,
				1211,
				1211,
				1931,
				1211,
				1015,
				1061,
				1170,
				5,
				1108,
				1198,
				1214,
				7,
				1092,
				6,
				4,
				1174,
				1319,
				1214,
				1285,
				1244,
				7,
				5,
				4,
				1171,
				1205,
				4,
				3,
				1283,
				1432,
				1016,
				1132,
				915,
				980,
				1197,
				1218,
				6,
				7,
				4,
				1164,
				7,
				1296,
				1248,
				8,
				1007,
				1057,
				9,
				1197,
				982,
				6,
				927,
				8,
				1079,
				8,
				1195,
				1216,
				6,
				1197,
				7,
				5,
				1182,
				5,
				4,
				1180,
				6,
				2634,
				8,
				1807,
				6,
				5,
				4,
				3,
				2620,
				7,
				4,
				1015,
				7,
				4,
				3,
				1201,
				1206,
				1217,
				1214,
				8,
				4,
				4,
				5,
				2,
				2,
				3,
				3,
				3,
				1194,
				1224,
				1212,
				1284,
				4,
				4,
				3,
				3,
				1201,
				7,
				1193,
				7,
				4,
				3,
				3,
				2900,
				6,
				1609,
				2755,
				10,
				1271,
				1752,
				1225,
				1203,
				7,
				4,
				1184,
				10,
				4,
				3,
				3,
				3,
				3,
				2,
				3,
				3,
				3,
				4,
				2,
				4,
				2,
				2,
				2,
				3,
				3,
				1189,
				4,
				1105,
				1214,
				9,
				1094,
				1215,
				6437,
				7,
				1505,
				7,
				1407,
				5,
				4,
				1003,
				6,
				4,
				3,
				4,
				1137,
				7,
				4,
				4,
				3,
				1151,
				7,
				4,
				3,
				1068,
				8,
				1816,
				7,
				4,
				3,
				3,
				1157,
				7,
				4,
				4,
				3,
				3,
				3,
				2,
				3,
				2,
				2,
				2,
				3,
				2,
				1155,
				6,
				1201,
				8,
				4,
				2158,
				8263,
				7,
				5,
				4,
				1070,
				8,
				4,
				1136,
				5,
				4,
				4,
				3,
				2,
				1149,
				7,
				1296,
				5,
				4,
				3,
				3,
				1159,
				8,
				1237,
				5,
				3,
				4,
				3,
				3,
				2,
				1142,
				6,
				6,
				5,
				7,
				3,
				3,
				2,
				1178,
				7,
				4,
				3,
				3,
				2,
				3,
				3,
				1119,
				7,
				5,
				4,
				3,
				3,
				2,
				3,
				3,
				2,
				2,
				3,
				3,
				3,
				3,
				2,
				3,
				1228,
				6,
				4,
				3,
				3,
				3,
				2,
				2,
				3,
				2,
				2,
				3,
				3,
				3,
				2591,
				8,
				2942,
				6,
				4,
				3,
				1590,
				5,
				4,
				4,
				1879,
				7,
				4,
				4,
				3,
				3,
				3,
				1237,
				7,
				4,
				3,
				3,
				3,
				3,
				2,
				3,
				1110,
				8,
				4,
				4,
				4,
				2,
				2,
				3,
				2,
				2,
				3,
				2,
				2,
				3,
				2,
				2,
				2,
				4,
				3,
				2,
				3,
				3,
				3,
				3,
				1137,
				3,
				3,
				4,
				1087,
				6,
				5,
				3,
				1171,
				6,
				4,
				5,
				3,
				4,
				2,
				2,
				1226,
				8,
				3,
				3,
				4,
				3,
				2,
				2,
				3,
				2,
				2,
				3,
				3,
				3,
				4,
				2,
				2,
				5,
				2,
				1100,
				3,
				2,
				3,
				3,
				2,
				2,
				2,
				4,
				3,
				4,
				3,
				2,
				2,
				3,
				3,
				2,
				3,
				2,
				4,
				2,
				3,
				2,
				3,
				2,
				2,
				3,
				2,
				3,
				3,
				2,
				3,
				2,
				2,
				3,
				3,
				2,
				4,
				2,
				2223,
				3,
				3,
				3,
				3,
				3,
				2,
				3,
				3,
				3,
				3,
				3,
				2,
				3,
				2,
				2,
				2,
				1151,
				3,
				3,
				3,
				1188,
				5,
				4,
				4,
				3,
				2,
				4,
				3,
				3,
				2,
				2,
				4,
				3,
				2,
				3,
				1248,
				7,
				4,
				3,
				1173,
				5,
				4,
				3,
				5,
				2,
				3,
				3,
				3,
				2,
				2,
				3,
				2,
				3,
				4,
				3,
				3,
				1228,
				4,
				5,
				5,
				2,
				2,
				3,
				2,
				2,
				3,
				2,
				3,
				3,
				3,
				3,
				3,
				2,
				2,
				2,
				3,
				4,
				3,
				2,
				2,
				3,
				3,
				2,
				3,
				3,
				2,
				3,
				3,
				2,
				2,
				3,
				4,
				6,
				3,
				5,
				3,
				3,
				3,
				2,
				2,
				4,
				2,
				2,
				3,
				2,
				2,
				3,
				2,
				2,
				3,
				2,
				3,
				3,
				2,
				2,
				3,
				3,
				3,
				3,
				2,
				3,
				2,
				2,
				3,
				3,
				2,
				3,
				2,
				3,
				6,
				2,
				3,
				3,
				4,
				2,
				3,
				4,
				1706,
				3,
				3,
				3,
				3,
				4,
				3,
				3,
				3,
				2,
				3,
				2,
				3,
				5,
				3,
				2,
				3,
				2,
				1229,
				3,
				4,
				3,
				2,
				3,
				2,
				3,
				3,
				2,
				2,
				3,
				5,
				3,
				3,
				2,
				3,
				3,
				4,
				2,
				3,
				2,
				3,
				3,
				2,
				2,
				3,
				2,
				3,
				2,
				2,
				3,
				3,
				2,
				3,
				3,
				3,
				4,
				2,
				3,
				3,
				4,
				2,
				3,
				2,
				1222,
				3,
				2,
				3,
				3,
				4,
				2,
				3,
				3,
				2,
				3,
				4,
				2,
				2,
				4,
				3,
				3,
				3,
				5,
				2,
				3,
				3,
				2,
				4,
				2,
				2,
				4,
				4,
				3,
				5,
				2,
				2,
				3,
				2092,
				3,
				3,
				3,
				3,
				4,
				3,
				3,
				3,
				3,
				3,
				4,
				2,
				3,
				2,
				3,
				2,
				4,
				3,
				2,
				3,
				2,
				2,
				3,
				2,
				3,
				2,
				2,
				2,
				2,
				3,
				3,
				2,
				3,
				2,
				2,
				2,
				4,
				3,
				3,
				2,
				2,
				3,
				3,
				2,
				3,
				3,
				2,
				2,
				3,
				2,
				2,
				3,
				2,
				2,
				2,
				2,
				2,
				4,
				2,
				3,
				3,
				3,
				2,
				4,
				2,
				3,
				2,
				2,
				3,
				2,
				2,
				3,
				2,
				4,
				3,
				2,
				4,
				3,
				2567,
				3,
				4,
				3,
				4,
				3,
				3,
				2,
				2,
				2,
				3,
				2,
				3,
				3,
				2,
				3,
				3,
				2,
				4,
				3,
				4,
				4,
				3,
				3,
				2,
				4,
				2,
				4,
				3,
				2,
				2,
				2,
				2,
				3,
				2,
				2,
				2,
				4,
				2,
				2,
				4,
				2,
				2,
				4,
				3,
				2,
				3,
				2,
				6,
				2,
				3,
				3,
				3,
				2,
				2,
				2,
				3,
				2,
				3,
				4,
				3,
				3,
				2,
				3,
				2,
				3,
				4,
				2,
				2,
				5,
				2,
				2,
				3,
				2,
				1205,
				3,
				3,
				3,
				3,
				2,
				3,
				5,
				2,
				3,
				3,
				2,
				3,
				3,
				4,
				3,
				3,
				3,
				2,
				3,
				3,
				5,
				3,
				2,
				2,
				5,
				3,
				3,
				3,
				5,
				2,
				2,
				4,
				2,
				3,
				3,
				2,
				2,
				2,
				2,
				2,
				2,
				2,
				4,
				2,
				3,
				3,
				3,
				3,
				3,
				3,
				3,
				5,
				4,
				2,
				6,
				3,
				2,
				2,
				3,
				3,
				2,
				4,
				3,
				3,
				3,
				3,
				3,
				4,
				3,
				3,
				3,
				3,
				2,
				3,
				4,
				3,
				3,
				3,
				2,
				2,
				2,
				8,
				3,
				4,
				2,
				3,
				2,
				2,
				3,
				3,
				3,
				3,
				3,
				3,
				3,
				3,
				3,
				3,
				2,
				4,
				3,
				2,
				3,
				3,
				3,
				3,
				3,
				4,
				3,
				4,
				3,
				3,
				4,
				4,
				3,
				3,
				3,
				2,
				4,
				2,
				14,
				2,
				3,
				3,
				2,
				4,
				3,
				6,
				3,
				3,
				3,
				3,
				2,
				4,
				3,
				3,
				5,
				3,
				2,
				4,
				6,
				2,
				3,
				6,
				3,
				3,
				3,
				3,
				3,
				3,
				3,
				4,
				3,
				4,
				5,
				3,
				2,
				3,
				10,
				3,
				3,
				3,
				5,
				3,
				20,
				5,
				4,
				2,
				2,
				2,
				2,
				2,
				2,
				2,
				3,
				3,
				2,
				2,
				6,
				3,
				2,
				3,
				3,
				3,
				3,
				4,
				3,
				3,
				3,
				4,
				2,
				5,
				3,
				2,
				3,
				4,
				3,
				4,
				3,
				3,
				3,
				3,
				3,
				4,
				17,
				3,
				2,
				3,
				2,
				3,
				3,
				3,
				4,
				3,
				2,
				3,
				3,
				3,
				5,
				4,
				4,
				3,
				3,
				3,
				3,
				4,
				3,
				2,
				3,
				3,
				3,
				3,
				2,
				5,
				3,
				6,
				2,
				2,
				4,
				3,
				2,
				3,
				3,
				4,
				3,
				3,
				2,
				4,
				4,
				3,
				3,
				3,
				3,
				3,
				6,
				3,
				4,
				2,
				3,
				3,
				3,
				3,
				3,
				2,
				4,
				4,
				3,
				2,
				4,
				3,
				3,
				3,
				3,
				6,
				3,
				3,
				3,
				2,
				3,
				5,
				3,
				4,
				2,
				2,
				2,
				2,
				2,
				2,
				2,
				2,
				2,
				3,
				3,
				3,
				3,
				2,
				3,
				3,
				3,
				5,
				2,
				2,
				3,
				2,
				5,
				3,
				3,
				3,
				3,
				3,
				3,
				3,
				3,
				3,
				4,
				3,
				3,
				5,
				6,
				3,
				5,
				11,
				3,
				4,
				3,
				3,
				5,
				6,
				3,
				5,
				3,
				3,
				3,
				2,
				3,
				4,
				6,
				4,
				22,
				4,
				3,
				3,
				2,
				2,
				2,
				2,
				2,
				2,
				4,
				3,
				3,
				4,
				9,
				4,
				2,
				3,
				6,
				3,
				3,
				3,
				3,
				2,
				2,
				3,
				2,
				3,
				3,
				5,
				2,
				3,
				2,
				3,
				3,
				2,
				5,
				3,
				3,
				3,
				3,
				4,
				3,
				4,
				3,
				3,
				2,
				3,
				6,
				3,
				3,
				3,
				3,
				4,
				2,
				3,
				3,
				7,
				3,
				3,
				3,
				3,
				4,
				3,
				4,
				3,
				3,
				2,
				3,
				3,
				3,
				3,
				3,
				5,
				3,
				4,
				3,
				3,
				17,
				2,
				3,
				4,
				3,
				5,
				3,
				2,
				3,
				3,
				11,
				3,
				3,
				2,
				3,
				4,
				4,
				3,
				3,
				3,
				13,
				2,
				4,
				3,
				7,
				3,
				3,
				6,
				3,
				2,
				3,
				5,
				4,
				3,
				3,
				2,
				5,
				4,
				3,
				2,
				3,
				2,
				3,
				3,
				4,
				3,
				5,
				4,
				4,
				5,
				5,
				2,
				2,
				3,
				3,
				3,
				3,
				2,
				2,
				3,
				3,
				3,
				3,
				3,
				2,
				3,
				3,
				5,
				4,
				3,
				2,
				3,
				2,
				2,
				4,
				2,
				3,
				3,
				2,
				3,
				3,
				2,
				15,
				2,
				3,
				3,
				2,
				3,
				3,
				4,
				4,
				3,
				3,
				4,
				3,
				2,
				3,
				3,
				13,
				2,
				2,
				3,
				2,
				3,
				3,
				4,
				3,
				2,
				2,
				2,
				3,
				2,
				2,
				2,
				2,
				3,
				3,
				3,
				5,
				3,
				2,
				4,
				3,
				3,
				3,
				3,
				2,
				3,
				3,
				3,
				2,
				3,
				2,
				3,
				8,
				7,
				3,
				2,
				3,
				3,
				3,
				4,
				3,
				3,
				2,
				3,
				3,
				3,
				3,
				2,
				3,
				3,
				2,
				3,
				3,
				2,
				3,
				3,
				5,
				3,
				3,
				3,
				5,
				3,
				4,
				3,
				2,
				3,
				4,
				5,
				3,
				3,
				3,
				3,
				2,
				3,
				5,
				4,
				3,
				6,
				2,
				3,
				3,
				6,
				3,
				2,
				3,
				3,
				2,
				3,
				3,
				2,
				7,
				3,
				3,
				4,
				3,
				3,
				2,
				4,
				4,
				2,
				2,
				4,
				4,
				3,
				7,
				2,
				3,
				3,
				3,
				3,
				3,
				3,
				3,
				6,
				3,
				3,
				3,
				3,
				3,
				2,
				5,
				3,
				2,
				6,
				6,
				3,
				2,
				3,
				3,
				3,
				3,
				6,
				3,
				4,
				4,
				2,
				3,
				3,
				2,
				4,
				3,
				3,
				3,
				2,
				3,
				3,
				3,
				7,
				4,
				3,
				2,
				4,
				4,
				2,
				3,
				3,
				3,
				2,
				3,
				3,
				3,
				3,
				3,
				3,
				3,
				2,
				2,
				3,
				2,
				2,
				4,
				3,
				2,
				4,
				4,
				5,
				11,
				2,
				2,
				2,
				2,
				2,
				2,
				2,
				3,
				2,
				2,
				3,
				3,
				2,
				5,
				2,
				2,
				2,
				2,
				2,
				2,
				3,
				2,
				3,
				2,
				2,
				2,
				2,
				4,
				3,
				4,
				3,
				3,
				3,
				6,
				5,
				5,
				3,
				3,
				3,
				3,
				3,
				3,
				3,
				4,
				3,
				3,
				3,
				3,
				7,
				4,
				3,
				3,
				6,
				2,
				3,
				4,
				3,
				3,
				4,
				3,
				2,
				3,
				4,
				2,
				4,
				2,
				4,
				4,
				3,
				4,
				2,
				3,
				3,
				2,
				2,
				5,
				2,
				3,
				2,
				5,
				3,
				3,
				3,
				5,
				2,
				2,
				4,
				4,
				4,
				3,
				3,
				3,
				4,
				3,
				2,
				4,
				2,
				5,
				2,
				6,
				3,
				2,
				3,
				3,
				3,
				3,
				3,
				2,
				3,
				3,
				3,
				3,
				2,
				5,
				3,
				3,
				2,
				4,
				2,
				3,
				3,
				2,
				3,
				3,
				3,
				2,
				3,
				3,
				2,
				3,
				2,
				3,
				17,
				2,
				3,
				3,
				2,
				4,
				3,
				2,
				5,
				3,
				3,
				2,
				3,
				6,
				3,
				2,
				4,
				2,
				3,
				4,
				3,
				4,
				2,
				3,
				3,
				3,
				3,
				4,
				5,
				4,
				2,
				3,
				5,
				5,
				2,
				3,
				3,
				3,
				3,
				3,
				3,
				4,
				3,
				3,
				12,
				3,
				2,
				2,
				2,
				2,
				2,
				2,
				2,
				2,
				3,
				2,
				3,
				2,
				2,
				3,
				3,
				2,
				3,
				3,
				2,
				4,
				2,
				3,
				3,
				4,
				3,
				3,
				3,
				3,
				3,
				3,
				4,
				3,
				3,
				3,
				5,
				2,
				3,
				4,
				2,
				3,
				4,
				2,
				3,
				3,
				3,
				3,
				5,
				2,
				4,
				3,
				3,
				3,
				3,
				3,
				4,
				3,
				3,
				4,
				3,
				3,
				4,
				3,
				3,
				6,
				2,
				3,
				3,
				3,
				2,
				3,
				2,
				2,
				3,
				2,
				2,
				3,
				3,
				5,
				3,
				2,
				6,
				3,
				3,
				2,
				5,
				3,
				3,
				3,
				3,
				3,
				3,
				3,
				4,
				2,
				3,
				3,
				3,
				3,
				3,
				2,
				3,
				6,
				2,
				4,
				3,
				3,
				3,
				2,
				3,
				3,
				3,
				3,
				2,
				4,
				3,
				4,
				1255,
				4,
				5,
				2,
				3,
				3,
				2,
				4,
				3,
				2,
				3,
				3,
				3,
				3,
				2,
				2,
				7,
				3,
				3,
				3,
				3,
				4,
				3,
				5,
				3,
				4,
				3,
				3,
				3,
				5,
				3,
				4,
				2,
				3,
				4,
				3,
				2,
				3,
				5,
				2,
				4,
				2,
				2,
				2,
				3,
				2,
				2,
				3,
				3,
				3,
				3,
				3,
				3,
				3,
				3,
				2,
				3,
				8,
				4,
				3,
				2,
				2,
				5,
				2,
				2,
				2,
				2,
				2,
				3,
				3,
				2,
				2,
				3,
				3,
				6,
				3,
				2,
				3,
				3,
				3,
				3,
				3,
				2,
				3,
				3,
				2,
				3,
				3,
				8,
				4,
				3,
				3,
				2,
				3,
				3,
				3,
				3,
				4,
				3,
				3,
				4,
				6,
				2,
				3,
				3,
				3,
				2,
				7,
				3,
				3,
				3,
				4,
				3,
				3,
				3,
				3,
				3,
				4,
				3,
				3,
				5,
				3,
				2,
				3,
				4,
				5,
				3,
				5,
				5,
				3,
				3,
				2,
				4,
				2,
				3,
				3,
				4,
				3,
				3,
				5,
				3,
				3,
				3,
				2,
				3,
				3,
				3,
				3,
				3,
				3,
				3,
				3,
				3,
				3,
				3,
				2,
				3,
				3,
				3,
				4,
				3,
				3,
				2,
				3,
				6,
				13,
				3,
				3,
				7,
				3,
				4,
				4,
				16,
				4,
				3,
				3,
				4,
				4,
				3,
				8,
				7,
				4,
				3,
				2,
				4,
				2,
				3,
				3,
				3,
				4,
				3,
				3,
				2,
				3,
				3,
				7,
				3,
				2,
				2,
				3,
				4,
				4,
				3,
				3,
				3,
				2,
				7,
				3,
				3,
				3,
				3,
				3,
				3,
				7,
				3,
				3,
				3,
				2,
				3,
				4,
				2,
				3,
				3,
				3,
				2,
				3,
				3,
				9,
				2,
				3,
				2,
				2,
				2,
				2,
				3,
				2,
				2,
				4,
				2,
				3,
				2,
				3,
				3,
				4,
				4,
				3,
				3,
				2,
				3,
				3,
				3,
				5,
				2,
				3,
				4,
				3,
				2,
				3,
				4,
				4,
				3,
				3,
				2,
				3,
				3,
				5,
				2,
				3,
				4,
				3,
				6,
				4,
				4,
				4,
				3,
				3,
				2,
				2,
				4,
				2,
				3,
				3,
				4,
				3,
				3,
				2,
				2,
				3,
				3,
				3,
				3,
				3,
				2,
				5,
				3,
				3,
				3,
				10,
				4,
				4,
				2,
				3,
				2,
				3,
				3,
				2,
				2,
				3,
				3,
				2,
				3,
				2,
				2,
				6,
				3,
				3,
				3,
				3,
				5,
				3,
				3,
				3,
				4,
				3,
				3,
				3,
				3,
				3,
				3,
				5,
				3,
				2,
				5,
				4,
				3,
				3,
				4,
				2,
				3,
				4,
				5,
				2,
				5,
				3,
				3,
				3,
				4,
				5,
				3,
				2,
				3,
				4,
				3,
				3,
				2,
				3,
				6,
				2,
				3,
				2,
				5,
				3,
				4,
				2,
				3,
				3,
				3,
				3,
				2,
				4,
				3,
				3,
				3,
				5,
				3,
				3,
				3,
				2,
				5,
				3,
				3,
				3,
				10,
				3,
				3,
				2,
				2,
				3,
				2,
				3,
				6,
				4,
				2,
				4,
				2,
				3,
				3,
				2,
				3,
				4,
				3,
				4,
				3,
				3,
				5,
				2,
				2,
				3,
				2,
				11,
				5,
				2,
				2,
				2,
				2,
				2,
				2,
				5,
				4,
				2,
				3,
				2,
				4,
				3,
				3,
				3,
				3,
				4,
				3,
				6,
				3,
				3,
				3,
				3,
				2,
				4,
				3,
				2,
				6,
				3,
				3,
				2,
				7,
				3,
				2,
				4,
				3,
				3,
				3,
				3,
				3,
				4,
				2,
				5,
				3,
				3,
				5,
				2,
				4,
				2,
				3,
				4,
				2,
				3,
				4,
				2,
				2,
				2,
				2,
				2,
				2,
				2,
				2,
				3,
				2,
				3,
				2,
				3,
				5,
				3,
				3,
				3,
				2,
				3,
				3,
				3,
				3,
				2,
				3,
				3,
				3,
				3,
				2,
				3,
				2,
				4,
				3,
				3,
				3,
				3,
				3,
				3,
				4,
				2,
				5,
				2,
				4,
				3,
				3,
				3,
				3,
				3,
				3,
				2,
				3,
				3,
				2,
				3,
				3,
				2,
				4,
				3,
				3,
				3,
				5,
				3,
				2,
				3,
				4,
				2,
				3,
				4,
				2,
				3,
				3,
				3,
				3,
				2,
				3,
				3,
				3,
				3,
				4,
				3,
				5,
				3,
				2,
				2,
				3,
				3,
				3,
				7,
				3,
				3,
				3,
				4,
				2,
				3,
				3,
				4,
				3,
				3,
				3,
				4,
				2,
				3,
				3,
				2,
				5,
				5,
				5,
				3,
				4,
				3,
				2,
				14,
				3,
				2,
				2,
				2,
				2,
				2,
				2,
				2,
				2,
				3,
				2,
				3,
				5,
				4,
				2,
				3,
				2,
				4,
				3,
				3,
				2,
				3,
				3,
				3,
				5,
				3,
				2,
				3,
				3,
				3,
				3,
				4,
				4,
				3,
				4,
				3,
				3,
				15,
				3,
				3,
				3,
				3,
				3,
				5,
				2,
				3,
				3,
				3,
				3,
				3,
				2,
				6,
				3,
				2,
				5,
				3,
				3,
				3,
				2,
				3,
				3,
				3,
				3,
				3,
				3,
				2,
				2,
				3,
				3,
				3,
				3,
				2,
				3,
				3,
				3,
				3,
				3,
				2,
				2,
				3,
				3,
				3,
				2,
				5,
				3,
				7,
				3,
				2,
				3,
				2,
				2,
				3,
				4,
				2,
				4,
				4,
				3,
				3,
				4,
				2,
				3,
				3,
				3,
				2,
				4,
				2,
				3,
				5,
				3,
				3,
				6,
				2,
				2,
				3,
				4,
				3,
				2,
				6,
				4,
				2,
				4,
				2,
				6,
				2,
				2,
				4,
				2,
				2,
				3,
				3,
				3,
				3,
				2,
				6,
				4,
				2,
				3,
				3,
				3,
				5,
				3,
				4,
				3,
				3,
				3,
				8,
				3,
				3,
				2,
				3,
				3,
				3,
				3,
				2,
				2,
				3,
				2,
				5,
				3,
				3,
				2,
				3,
				4,
				2,
				3,
				3,
				2,
				11,
				6,
				2,
				2,
				2,
				2,
				2,
				2,
				2,
				2,
				2,
				2,
				3,
				2,
				3,
				5,
				2,
				2,
				6,
				2,
				2,
				20,
				2,
				3,
				4,
				2,
				2,
				4,
				3,
				3,
				5,
				3,
				2,
				3,
				4,
				4,
				2,
				6,
				5,
				2,
				4,
				3,
				3,
				4,
				4,
				3,
				3,
				4,
				3,
				2,
				3,
				2,
				3,
				3,
				6,
				4,
				3,
				3,
				4,
				2,
				4,
				3,
				4,
				8,
				5,
				3,
				3,
				2,
				3,
				6,
				3,
				2,
				2,
				5,
				3,
				3,
				3,
				3,
				3,
				6,
				3,
				3,
				2,
				3,
				4,
				3,
				5,
				8,
				10,
				3,
				6,
				3,
				3,
				5,
				3,
				2,
				3,
				3,
				5,
				3,
				5,
				3,
				2,
				3,
				3,
				3,
				3,
				11,
				2,
				3,
				2,
				4,
				3,
				3,
				9,
				2,
				3,
				3,
				3,
				4,
				3,
				9,
				3,
				3,
				3,
				3,
				3,
				4,
				5,
				2,
				3,
				5,
				3,
				3,
				5,
				2,
				4,
				2,
				2,
				3,
				2,
				3,
				3,
				3,
				2,
				3,
				3,
				2,
				5,
				2,
				2,
				3,
				7,
				3,
				2,
				2,
				3,
				3,
				3,
				2,
				3,
				3,
				6,
				2,
				3,
				4,
				3,
				4,
				2,
				4,
				5,
				2,
				4,
				3,
				2,
				6,
				9,
				3,
				3,
				3,
				2,
				4,
				2,
				3,
				2,
				2,
				3,
				3,
				2,
				5,
				3,
				3,
				3,
				3,
				3,
				3,
				3,
				4,
				3,
				4,
				10,
				3,
				3,
				3,
				3,
				4,
				2,
				4,
				3,
				3,
				3,
				4,
				2,
				4,
				3,
				3,
				5,
				3,
				4,
				3,
				3,
				5,
				4,
				3,
				5,
				3,
				3,
				3,
				5,
				3,
				2,
				3,
				3,
				3,
				13,
				3,
				3,
				3,
				3,
				3,
				6,
				3,
				3,
				6,
				4,
				2,
				2,
				4,
				2,
				3,
				3,
				3,
				3,
				3,
				2,
				3,
				6,
				4,
				11,
				3,
				3,
				2,
				3,
				3,
				3,
				2,
				3,
				6,
				4,
				2,
				3,
				2,
				3,
				3,
				3,
				2,
				5,
				8,
				5,
				5,
				5,
				3,
				3,
				3,
				4,
				3,
				3,
				3,
				4,
				3,
				9,
				5,
				2,
				3,
				3,
				4,
				2,
				3,
				3,
				3,
				3,
				2,
				3,
				6,
				3,
				2,
				3,
				3,
				3,
				5,
				2,
				2,
				3,
				2,
				3,
				3,
				2,
				2,
				4,
				2,
				5,
				2,
				3,
				3,
				2,
				4,
				4,
				2,
				3,
				3,
				5,
				4,
				3,
				2,
				3,
				3,
				3,
				3,
				3,
				3,
				2,
				3,
				2,
				3,
				3,
				4,
				2,
				3,
				18,
				3,
				2,
				3,
				2,
				3,
				2,
				2,
				2,
				2,
				2,
				4,
				5,
				2,
				3,
				5,
				2,
				3,
				3,
				4,
				4,
				2,
				5,
				3,
				3,
				4,
				3,
				3,
				3,
				4,
				2,
				2,
				3,
				3,
				3,
				3,
				4,
				3,
				4,
				6,
				3,
				3,
				2,
				2,
				3,
				4,
				2,
				4,
				3,
				3,
				3,
				3,
				3,
				3,
				3,
				3,
				3,
				14,
				2,
				3,
				2,
				2,
				3,
				3,
				2,
				3,
				3,
				2,
				3,
				4,
				3,
				3,
				2,
				2,
				4,
				3,
				3,
				3,
				3,
				3,
				4,
				2,
				3,
				3,
				6,
				3,
				2,
				3,
				3,
				2,
				5,
				3,
				3,
				3,
				4,
				3,
				3,
				3,
				3,
				3,
				3,
				3,
				3,
				3,
				3,
				2,
				5,
				7,
				4
			],
			"allTests": [
				{},
				{},
				{},
				{},
				{},
				{},
				{},
				{},
				{},
				{},
				{},
				{},
				{},
				{},
				{},
				{},
				{},
				{},
				{},
				{},
				{},
				{},
				{},
				{},
				{},
				{},
				{},
				{},
				{},
				{},
				{},
				{},
				{},
				{},
				{},
				{},
				{},
				{},
				{},
				{},
				{},
				{},
				{},
				{},
				{},
				{},
				{},
				{},
				{},
				{},
				{},
				{},
				{},
				{},
				{},
				{},
				{},
				{},
				{},
				{},
				{},
				{},
				{},
				{},
				{},
				{},
				{},
				{},
				{},
				{},
				{},
				{},
				{},
				{},
				{},
				{},
				{},
				{},
				{},
				{},
				{},
				{},
				{},
				{},
				{},
				{},
				{},
				{},
				{},
				{},
				{},
				{},
				{},
				{},
				{},
				{},
				{},
				{},
				{},
				{},
				{},
				{},
				{},
				{},
				{},
				{},
				{},
				{},
				{},
				{},
				{},
				{},
				{},
				{},
				{},
				{},
				{},
				{},
				{},
				{},
				{},
				{},
				{},
				{},
				{},
				{},
				{},
				{},
				{},
				{},
				{},
				{},
				{},
				{},
				{},
				{},
				{},
				{},
				{},
				{},
				{},
				{},
				{},
				{},
				{},
				{},
				{},
				{},
				{},
				{},
				{},
				{},
				{},
				{},
				{},
				{},
				{},
				{},
				{},
				{},
				{},
				{},
				{},
				{},
				{},
				{},
				{},
				{},
				{},
				{},
				{},
				{},
				{},
				{},
				{},
				{},
				{},
				{},
				{},
				{},
				{},
				{},
				{},
				{},
				{},
				{},
				{},
				{},
				{},
				{},
				{},
				{},
				{},
				{},
				{},
				{},
				{},
				{},
				{},
				{},
				{},
				{},
				{},
				{},
				{},
				{},
				{},
				{},
				{},
				{},
				{},
				{},
				{},
				{},
				{},
				{},
				{},
				{},
				{},
				{},
				{},
				{},
				{},
				{},
				{},
				{},
				{},
				{},
				{},
				{},
				{},
				{},
				{},
				{},
				{},
				{},
				{},
				{},
				{},
				{},
				{},
				{},
				{},
				{},
				{},
				{},
				{},
				{},
				{},
				{},
				{},
				{},
				{},
				{},
				{},
				{},
				{},
				{},
				{},
				{},
				{},
				{},
				{},
				{},
				{},
				{},
				{},
				{},
				{},
				{},
				{},
				{},
				{},
				{},
				{},
				{},
				{},
				{},
				{},
				{},
				{},
				{},
				{},
				{},
				{},
				{},
				{},
				{},
				{},
				{},
				{},
				{},
				{},
				{},
				{},
				{},
				{},
				{},
				{},
				{},
				{},
				{},
				{},
				{},
				{},
				{},
				{},
				{},
				{},
				{},
				{},
				{},
				{},
				{},
				{},
				{},
				{},
				{},
				{},
				{},
				{},
				{},
				{},
				{},
				{},
				{},
				{},
				{},
				{},
				{},
				{},
				{},
				{},
				{},
				{},
				{},
				{},
				{},
				{},
				{},
				{},
				{},
				{},
				{},
				{},
				{},
				{},
				{},
				{},
				{},
				{},
				{},
				{},
				{},
				{},
				{},
				{},
				{},
				{},
				{},
				{},
				{},
				{},
				{},
				{},
				{},
				{},
				{},
				{},
				{},
				{},
				{},
				{},
				{},
				{},
				{},
				{},
				{},
				{},
				{},
				{},
				{},
				{},
				{},
				{},
				{},
				{},
				{},
				{},
				{},
				{},
				{},
				{},
				{},
				{},
				{},
				{},
				{},
				{},
				{},
				{},
				{},
				{},
				{},
				{},
				{},
				{},
				{},
				{},
				{},
				{},
				{},
				{},
				{},
				{},
				{},
				{},
				{},
				{},
				{},
				{},
				{},
				{},
				{},
				{},
				{},
				{},
				{},
				{},
				{},
				{},
				{},
				{},
				{},
				{},
				{},
				{},
				{},
				{},
				{},
				{},
				{},
				{},
				{},
				{},
				{},
				{},
				{},
				{},
				{},
				{},
				{},
				{},
				{},
				{},
				{},
				{},
				{},
				{},
				{},
				{},
				{},
				{},
				{},
				{},
				{},
				{},
				{},
				{},
				{},
				{},
				{},
				{},
				{},
				{},
				{},
				{},
				{},
				{},
				{},
				{},
				{},
				{},
				{},
				{},
				{},
				{},
				{},
				{},
				{},
				{},
				{},
				{},
				{},
				{},
				{},
				{},
				{},
				{},
				{},
				{},
				{},
				{},
				{},
				{},
				{},
				{},
				{},
				{},
				{},
				{},
				{},
				{},
				{},
				{},
				{},
				{},
				{},
				{},
				{},
				{},
				{},
				{},
				{},
				{},
				{},
				{},
				{},
				{},
				{},
				{},
				{},
				{},
				{},
				{},
				{},
				{},
				{},
				{},
				{},
				{},
				{},
				{},
				{},
				{},
				{},
				{},
				{},
				{},
				{},
				{},
				{},
				{},
				{},
				{},
				{},
				{},
				{},
				{},
				{},
				{},
				{},
				{},
				{},
				{},
				{},
				{},
				{},
				{},
				{},
				{},
				{},
				{},
				{},
				{},
				{},
				{},
				{},
				{},
				{},
				{},
				{},
				{},
				{},
				{},
				{},
				{},
				{},
				{},
				{},
				{},
				{},
				{},
				{},
				{},
				{},
				{},
				{},
				{},
				{},
				{},
				{},
				{},
				{},
				{},
				{},
				{},
				{},
				{},
				{},
				{},
				{},
				{},
				{},
				{},
				{},
				{},
				{},
				{},
				{},
				{},
				{},
				{},
				{},
				{},
				{},
				{},
				{},
				{},
				{},
				{},
				{},
				{},
				{},
				{},
				{},
				{},
				{},
				{},
				{},
				{},
				{},
				{},
				{},
				{},
				{},
				{},
				{},
				{},
				{},
				{},
				{},
				{},
				{},
				{},
				{},
				{},
				{},
				{},
				{},
				{},
				{},
				{},
				{},
				{},
				{},
				{},
				{},
				{},
				{},
				{},
				{},
				{},
				{},
				{},
				{},
				{},
				{},
				{},
				{},
				{},
				{},
				{},
				{},
				{},
				{},
				{},
				{},
				{},
				{},
				{},
				{},
				{},
				{},
				{},
				{},
				{},
				{},
				{},
				{},
				{},
				{},
				{},
				{},
				{},
				{},
				{},
				{},
				{},
				{},
				{},
				{},
				{},
				{},
				{},
				{},
				{},
				{},
				{},
				{},
				{},
				{},
				{},
				{},
				{},
				{},
				{},
				{},
				{},
				{},
				{},
				{},
				{},
				{},
				{},
				{},
				{},
				{},
				{},
				{},
				{},
				{},
				{},
				{},
				{},
				{},
				{},
				{},
				{},
				{},
				{},
				{},
				{},
				{},
				{},
				{},
				{},
				{},
				{},
				{},
				{},
				{},
				{},
				{},
				{},
				{},
				{},
				{},
				{},
				{},
				{},
				{},
				{},
				{},
				{},
				{},
				{},
				{},
				{},
				{},
				{},
				{},
				{},
				{},
				{},
				{},
				{},
				{},
				{},
				{},
				{},
				{},
				{},
				{},
				{},
				{},
				{},
				{},
				{},
				{},
				{},
				{},
				{},
				{},
				{},
				{},
				{},
				{},
				{},
				{},
				{},
				{},
				{},
				{},
				{},
				{},
				{},
				{},
				{},
				{},
				{},
				{},
				{},
				{},
				{},
				{},
				{},
				{},
				{},
				{},
				{},
				{},
				{},
				{},
				{},
				{},
				{},
				{},
				{},
				{},
				{},
				{},
				{},
				{},
				{},
				{},
				{},
				{},
				{},
				{},
				{},
				{},
				{},
				{},
				{},
				{},
				{},
				{},
				{},
				{},
				{},
				{},
				{},
				{},
				{},
				{},
				{},
				{},
				{},
				{},
				{},
				{},
				{},
				{},
				{},
				{},
				{},
				{},
				{},
				{},
				{},
				{},
				{},
				{},
				{},
				{},
				{},
				{},
				{},
				{},
				{},
				{},
				{},
				{},
				{},
				{},
				{},
				{},
				{},
				{},
				{},
				{},
				{},
				{},
				{},
				{},
				{},
				{},
				{},
				{},
				{},
				{},
				{},
				{},
				{},
				{},
				{},
				{},
				{},
				{},
				{},
				{},
				{},
				{},
				{},
				{},
				{},
				{},
				{},
				{},
				{},
				{},
				{},
				{},
				{},
				{},
				{},
				{},
				{},
				{},
				{},
				{},
				{},
				{},
				{},
				{},
				{},
				{},
				{},
				{},
				{},
				{},
				{},
				{},
				{},
				{},
				{},
				{},
				{},
				{},
				{},
				{},
				{},
				{},
				{},
				{},
				{},
				{},
				{},
				{},
				{},
				{},
				{},
				{},
				{},
				{},
				{},
				{},
				{},
				{},
				{},
				{},
				{},
				{},
				{},
				{},
				{},
				{},
				{},
				{},
				{},
				{},
				{},
				{},
				{},
				{},
				{},
				{},
				{},
				{},
				{},
				{},
				{},
				{},
				{},
				{},
				{},
				{},
				{},
				{},
				{},
				{},
				{},
				{},
				{},
				{},
				{},
				{},
				{},
				{},
				{},
				{},
				{},
				{},
				{},
				{},
				{},
				{},
				{},
				{},
				{},
				{},
				{},
				{},
				{},
				{},
				{},
				{},
				{},
				{},
				{},
				{},
				{},
				{},
				{},
				{},
				{},
				{},
				{},
				{},
				{},
				{},
				{},
				{},
				{},
				{},
				{},
				{},
				{},
				{},
				{},
				{},
				{},
				{},
				{},
				{},
				{},
				{},
				{},
				{},
				{},
				{},
				{},
				{},
				{},
				{},
				{},
				{},
				{},
				{},
				{},
				{},
				{},
				{},
				{},
				{},
				{},
				{},
				{},
				{},
				{},
				{},
				{},
				{},
				{},
				{},
				{},
				{},
				{},
				{},
				{},
				{},
				{},
				{},
				{},
				{},
				{},
				{},
				{},
				{},
				{},
				{},
				{},
				{},
				{},
				{},
				{},
				{},
				{},
				{},
				{},
				{},
				{},
				{},
				{},
				{},
				{},
				{},
				{},
				{},
				{},
				{},
				{},
				{},
				{},
				{},
				{},
				{},
				{},
				{},
				{},
				{},
				{},
				{},
				{},
				{},
				{},
				{},
				{},
				{},
				{},
				{},
				{},
				{},
				{},
				{},
				{},
				{},
				{},
				{},
				{},
				{},
				{},
				{},
				{},
				{},
				{},
				{},
				{},
				{},
				{},
				{},
				{},
				{},
				{},
				{},
				{},
				{},
				{},
				{},
				{},
				{},
				{},
				{},
				{},
				{},
				{},
				{},
				{},
				{},
				{},
				{},
				{},
				{},
				{},
				{},
				{},
				{},
				{},
				{},
				{},
				{},
				{},
				{},
				{},
				{},
				{},
				{},
				{},
				{},
				{},
				{},
				{},
				{},
				{},
				{},
				{},
				{},
				{},
				{},
				{},
				{},
				{},
				{},
				{},
				{},
				{},
				{},
				{},
				{},
				{},
				{},
				{},
				{},
				{},
				{},
				{},
				{},
				{},
				{},
				{},
				{},
				{},
				{},
				{},
				{},
				{},
				{},
				{},
				{},
				{},
				{},
				{},
				{},
				{},
				{},
				{},
				{},
				{},
				{},
				{},
				{},
				{},
				{},
				{},
				{},
				{},
				{},
				{},
				{},
				{},
				{},
				{},
				{},
				{},
				{},
				{},
				{},
				{},
				{},
				{},
				{},
				{},
				{},
				{},
				{},
				{},
				{},
				{},
				{},
				{},
				{},
				{},
				{},
				{},
				{},
				{},
				{},
				{},
				{},
				{},
				{},
				{},
				{},
				{},
				{},
				{},
				{},
				{},
				{},
				{},
				{},
				{},
				{},
				{},
				{},
				{},
				{},
				{},
				{},
				{},
				{},
				{},
				{},
				{},
				{},
				{},
				{},
				{},
				{},
				{},
				{},
				{},
				{},
				{},
				{},
				{},
				{},
				{},
				{},
				{},
				{},
				{},
				{},
				{},
				{},
				{},
				{},
				{},
				{},
				{},
				{},
				{},
				{},
				{},
				{},
				{},
				{},
				{},
				{},
				{},
				{},
				{},
				{},
				{},
				{},
				{},
				{},
				{},
				{},
				{},
				{},
				{},
				{},
				{},
				{},
				{},
				{},
				{},
				{},
				{},
				{},
				{},
				{},
				{},
				{},
				{},
				{},
				{},
				{},
				{},
				{},
				{},
				{},
				{},
				{},
				{},
				{},
				{},
				{},
				{},
				{},
				{},
				{},
				{},
				{},
				{},
				{},
				{},
				{},
				{},
				{},
				{},
				{},
				{},
				{},
				{},
				{},
				{},
				{},
				{},
				{},
				{},
				{},
				{},
				{},
				{},
				{},
				{},
				{},
				{},
				{},
				{},
				{},
				{},
				{},
				{},
				{},
				{},
				{},
				{},
				{},
				{},
				{},
				{},
				{},
				{},
				{},
				{},
				{},
				{},
				{},
				{},
				{},
				{},
				{},
				{},
				{},
				{},
				{},
				{},
				{},
				{},
				{},
				{},
				{},
				{},
				{},
				{},
				{},
				{},
				{},
				{},
				{},
				{},
				{},
				{},
				{},
				{},
				{},
				{},
				{},
				{},
				{},
				{},
				{},
				{},
				{},
				{},
				{},
				{},
				{},
				{},
				{},
				{},
				{},
				{},
				{},
				{},
				{},
				{},
				{},
				{},
				{},
				{},
				{},
				{},
				{},
				{},
				{},
				{},
				{},
				{},
				{},
				{},
				{},
				{},
				{},
				{},
				{},
				{},
				{},
				{},
				{},
				{},
				{},
				{},
				{},
				{},
				{},
				{},
				{},
				{},
				{},
				{},
				{},
				{},
				{},
				{},
				{},
				{},
				{},
				{},
				{},
				{},
				{},
				{},
				{},
				{},
				{},
				{},
				{},
				{},
				{},
				{},
				{},
				{},
				{},
				{},
				{},
				{},
				{},
				{},
				{},
				{},
				{},
				{},
				{},
				{},
				{},
				{},
				{},
				{},
				{},
				{},
				{},
				{},
				{},
				{},
				{},
				{},
				{},
				{},
				{},
				{},
				{},
				{},
				{},
				{},
				{},
				{},
				{},
				{},
				{},
				{},
				{},
				{},
				{},
				{},
				{},
				{},
				{},
				{},
				{},
				{},
				{},
				{},
				{},
				{},
				{},
				{},
				{},
				{},
				{},
				{},
				{},
				{},
				{},
				{},
				{},
				{},
				{},
				{},
				{},
				{},
				{},
				{},
				{},
				{},
				{},
				{},
				{},
				{},
				{},
				{},
				{},
				{},
				{},
				{},
				{},
				{},
				{},
				{},
				{},
				{},
				{},
				{},
				{},
				{},
				{},
				{},
				{},
				{},
				{},
				{},
				{},
				{},
				{},
				{},
				{},
				{},
				{},
				{},
				{},
				{},
				{},
				{},
				{},
				{},
				{},
				{},
				{},
				{},
				{},
				{},
				{},
				{},
				{},
				{},
				{},
				{},
				{},
				{},
				{},
				{},
				{},
				{},
				{},
				{},
				{},
				{},
				{},
				{},
				{},
				{},
				{},
				{},
				{},
				{},
				{},
				{},
				{},
				{},
				{},
				{},
				{},
				{},
				{},
				{},
				{},
				{},
				{},
				{},
				{},
				{},
				{},
				{},
				{},
				{},
				{},
				{},
				{},
				{},
				{},
				{},
				{},
				{},
				{},
				{},
				{},
				{},
				{},
				{},
				{},
				{},
				{},
				{},
				{},
				{},
				{},
				{},
				{},
				{},
				{},
				{},
				{},
				{},
				{},
				{},
				{},
				{},
				{},
				{},
				{},
				{},
				{},
				{},
				{},
				{},
				{},
				{},
				{},
				{},
				{},
				{},
				{},
				{},
				{},
				{},
				{},
				{},
				{},
				{},
				{},
				{},
				{},
				{},
				{},
				{},
				{},
				{},
				{},
				{},
				{},
				{},
				{},
				{},
				{},
				{},
				{},
				{},
				{},
				{},
				{},
				{},
				{},
				{},
				{},
				{},
				{},
				{},
				{},
				{},
				{},
				{},
				{},
				{},
				{},
				{},
				{},
				{},
				{},
				{},
				{},
				{},
				{},
				{},
				{},
				{},
				{},
				{},
				{},
				{},
				{},
				{},
				{},
				{},
				{},
				{},
				{},
				{},
				{},
				{},
				{},
				{},
				{},
				{},
				{},
				{},
				{},
				{},
				{},
				{},
				{},
				{},
				{},
				{},
				{},
				{},
				{},
				{},
				{},
				{},
				{},
				{},
				{},
				{},
				{},
				{},
				{},
				{},
				{},
				{},
				{},
				{},
				{},
				{},
				{},
				{},
				{},
				{},
				{},
				{},
				{},
				{},
				{},
				{},
				{},
				{},
				{},
				{},
				{},
				{},
				{},
				{},
				{},
				{},
				{},
				{},
				{},
				{},
				{},
				{},
				{},
				{},
				{},
				{},
				{},
				{},
				{},
				{},
				{},
				{},
				{},
				{},
				{},
				{},
				{},
				{},
				{},
				{},
				{},
				{},
				{},
				{},
				{},
				{},
				{},
				{},
				{},
				{},
				{},
				{},
				{},
				{},
				{},
				{},
				{},
				{},
				{},
				{},
				{},
				{},
				{},
				{},
				{},
				{},
				{},
				{},
				{},
				{},
				{},
				{},
				{},
				{},
				{},
				{},
				{},
				{},
				{},
				{},
				{},
				{},
				{},
				{},
				{},
				{},
				{},
				{},
				{},
				{},
				{},
				{},
				{},
				{},
				{},
				{},
				{},
				{},
				{},
				{},
				{},
				{},
				{},
				{},
				{},
				{},
				{},
				{},
				{},
				{},
				{},
				{},
				{},
				{},
				{},
				{},
				{},
				{},
				{},
				{},
				{},
				{},
				{},
				{},
				{},
				{},
				{},
				{},
				{},
				{},
				{},
				{},
				{},
				{},
				{},
				{},
				{},
				{},
				{},
				{},
				{},
				{},
				{},
				{},
				{},
				{},
				{},
				{},
				{},
				{},
				{},
				{},
				{},
				{},
				{},
				{},
				{},
				{},
				{},
				{},
				{},
				{},
				{},
				{},
				{},
				{},
				{},
				{},
				{},
				{},
				{},
				{},
				{},
				{},
				{},
				{},
				{},
				{},
				{},
				{},
				{},
				{},
				{},
				{},
				{},
				{},
				{},
				{},
				{},
				{},
				{},
				{},
				{},
				{},
				{},
				{},
				{},
				{},
				{},
				{},
				{},
				{},
				{},
				{},
				{},
				{},
				{},
				{},
				{},
				{},
				{},
				{},
				{},
				{},
				{},
				{},
				{},
				{},
				{},
				{},
				{},
				{},
				{},
				{},
				{},
				{},
				{},
				{},
				{},
				{},
				{},
				{},
				{},
				{},
				{},
				{},
				{},
				{},
				{},
				{},
				{},
				{},
				{},
				{},
				{},
				{},
				{},
				{},
				{},
				{},
				{},
				{},
				{},
				{},
				{},
				{},
				{},
				{},
				{},
				{},
				{},
				{},
				{},
				{},
				{},
				{},
				{},
				{},
				{},
				{},
				{},
				{},
				{},
				{},
				{},
				{},
				{},
				{},
				{},
				{},
				{},
				{},
				{},
				{},
				{},
				{},
				{},
				{},
				{},
				{},
				{},
				{},
				{},
				{},
				{},
				{},
				{},
				{},
				{},
				{},
				{},
				{},
				{},
				{},
				{},
				{},
				{},
				{},
				{},
				{},
				{},
				{},
				{},
				{},
				{},
				{},
				{},
				{},
				{},
				{},
				{},
				{},
				{},
				{},
				{},
				{},
				{},
				{},
				{},
				{},
				{},
				{},
				{},
				{},
				{},
				{},
				{},
				{},
				{},
				{},
				{},
				{},
				{},
				{},
				{},
				{},
				{},
				{},
				{},
				{},
				{},
				{},
				{},
				{},
				{},
				{},
				{},
				{},
				{},
				{},
				{},
				{},
				{},
				{},
				{},
				{},
				{},
				{},
				{},
				{},
				{},
				{},
				{},
				{},
				{},
				{},
				{},
				{},
				{},
				{},
				{},
				{},
				{},
				{},
				{},
				{},
				{},
				{},
				{},
				{},
				{},
				{},
				{},
				{},
				{},
				{},
				{},
				{},
				{},
				{},
				{},
				{},
				{},
				{},
				{},
				{},
				{},
				{},
				{},
				{},
				{},
				{},
				{},
				{},
				{},
				{},
				{},
				{},
				{},
				{},
				{},
				{},
				{},
				{},
				{},
				{},
				{},
				{},
				{},
				{},
				{},
				{},
				{},
				{},
				{},
				{},
				{},
				{},
				{},
				{},
				{},
				{},
				{},
				{},
				{},
				{},
				{},
				{},
				{},
				{},
				{},
				{},
				{},
				{},
				{},
				{},
				{},
				{},
				{},
				{},
				{},
				{},
				{},
				{},
				{},
				{},
				{},
				{},
				{},
				{},
				{},
				{},
				{},
				{},
				{},
				{},
				{},
				{},
				{},
				{},
				{},
				{},
				{},
				{},
				{},
				{},
				{},
				{},
				{},
				{},
				{},
				{},
				{},
				{},
				{},
				{},
				{},
				{},
				{},
				{},
				{},
				{},
				{},
				{},
				{},
				{},
				{},
				{},
				{},
				{},
				{},
				{},
				{},
				{},
				{},
				{},
				{},
				{},
				{},
				{},
				{},
				{},
				{},
				{},
				{},
				{},
				{},
				{},
				{},
				{},
				{},
				{},
				{},
				{},
				{},
				{},
				{},
				{},
				{},
				{},
				{},
				{},
				{},
				{},
				{},
				{},
				{},
				{},
				{},
				{},
				{},
				{},
				{},
				{},
				{},
				{},
				{},
				{},
				{},
				{},
				{},
				{},
				{},
				{},
				{},
				{},
				{},
				{},
				{},
				{},
				{},
				{},
				{},
				{},
				{},
				{},
				{},
				{},
				{},
				{},
				{},
				{},
				{},
				{},
				{},
				{},
				{},
				{},
				{},
				{},
				{},
				{},
				{},
				{},
				{},
				{},
				{},
				{},
				{},
				{},
				{},
				{},
				{},
				{},
				{},
				{},
				{},
				{},
				{},
				{},
				{},
				{},
				{},
				{},
				{},
				{},
				{},
				{},
				{},
				{},
				{},
				{},
				{},
				{},
				{},
				{},
				{},
				{},
				{},
				{},
				{},
				{},
				{},
				{},
				{},
				{},
				{},
				{},
				{},
				{},
				{},
				{},
				{},
				{},
				{},
				{},
				{},
				{},
				{},
				{},
				{},
				{},
				{},
				{},
				{},
				{},
				{},
				{},
				{},
				{},
				{},
				{},
				{},
				{},
				{},
				{},
				{},
				{},
				{},
				{},
				{},
				{},
				{},
				{},
				{},
				{},
				{},
				{},
				{},
				{},
				{},
				{},
				{},
				{},
				{},
				{},
				{},
				{},
				{},
				{},
				{},
				{},
				{},
				{},
				{},
				{},
				{},
				{},
				{},
				{},
				{},
				{},
				{},
				{},
				{},
				{},
				{},
				{},
				{},
				{},
				{},
				{},
				{},
				{},
				{},
				{},
				{},
				{},
				{},
				{},
				{},
				{},
				{},
				{},
				{},
				{},
				{},
				{},
				{},
				{},
				{},
				{},
				{},
				{},
				{},
				{},
				{},
				{},
				{},
				{},
				{},
				{},
				{},
				{},
				{},
				{},
				{},
				{},
				{},
				{},
				{},
				{},
				{},
				{},
				{},
				{},
				{},
				{},
				{},
				{},
				{},
				{},
				{},
				{},
				{},
				{},
				{},
				{},
				{},
				{},
				{},
				{},
				{},
				{},
				{},
				{},
				{},
				{},
				{},
				{},
				{},
				{},
				{},
				{},
				{},
				{},
				{},
				{},
				{},
				{},
				{},
				{},
				{},
				{},
				{},
				{},
				{},
				{},
				{},
				{},
				{},
				{},
				{},
				{},
				{},
				{},
				{},
				{},
				{},
				{},
				{},
				{},
				{},
				{},
				{},
				{},
				{},
				{},
				{},
				{},
				{},
				{},
				{},
				{},
				{},
				{},
				{},
				{},
				{},
				{},
				{},
				{},
				{},
				{},
				{},
				{},
				{},
				{},
				{},
				{},
				{},
				{},
				{},
				{},
				{},
				{},
				{},
				{},
				{},
				{},
				{},
				{},
				{},
				{},
				{},
				{},
				{},
				{},
				{},
				{},
				{},
				{},
				{},
				{},
				{},
				{},
				{},
				{},
				{},
				{},
				{},
				{},
				{},
				{},
				{},
				{},
				{},
				{},
				{},
				{},
				{},
				{},
				{},
				{},
				{},
				{},
				{},
				{},
				{},
				{},
				{},
				{},
				{},
				{},
				{},
				{},
				{},
				{},
				{},
				{},
				{},
				{},
				{},
				{},
				{},
				{},
				{},
				{},
				{},
				{},
				{},
				{},
				{},
				{},
				{},
				{},
				{},
				{},
				{},
				{},
				{},
				{},
				{},
				{},
				{},
				{},
				{},
				{},
				{},
				{},
				{},
				{},
				{},
				{},
				{},
				{},
				{},
				{},
				{},
				{},
				{},
				{},
				{},
				{},
				{},
				{},
				{},
				{},
				{},
				{},
				{},
				{},
				{},
				{},
				{},
				{},
				{},
				{},
				{},
				{},
				{},
				{},
				{},
				{},
				{},
				{},
				{},
				{},
				{},
				{},
				{},
				{},
				{},
				{},
				{},
				{},
				{},
				{},
				{},
				{},
				{},
				{},
				{},
				{},
				{},
				{},
				{},
				{},
				{},
				{},
				{},
				{},
				{},
				{},
				{},
				{},
				{},
				{},
				{},
				{},
				{},
				{},
				{},
				{},
				{},
				{},
				{},
				{},
				{},
				{},
				{},
				{},
				{},
				{},
				{},
				{},
				{},
				{},
				{},
				{},
				{},
				{},
				{},
				{},
				{},
				{},
				{},
				{},
				{},
				{},
				{},
				{},
				{},
				{},
				{},
				{},
				{},
				{},
				{},
				{},
				{},
				{},
				{},
				{},
				{},
				{},
				{},
				{},
				{},
				{},
				{},
				{},
				{},
				{},
				{},
				{},
				{},
				{},
				{},
				{},
				{},
				{},
				{},
				{},
				{},
				{},
				{},
				{},
				{},
				{},
				{},
				{},
				{},
				{},
				{},
				{},
				{},
				{},
				{},
				{},
				{},
				{},
				{},
				{},
				{},
				{},
				{},
				{},
				{},
				{},
				{},
				{},
				{},
				{},
				{},
				{},
				{},
				{},
				{},
				{},
				{},
				{},
				{},
				{},
				{},
				{},
				{},
				{},
				{},
				{},
				{},
				{},
				{},
				{},
				{},
				{},
				{},
				{},
				{},
				{},
				{},
				{},
				{},
				{},
				{},
				{},
				{},
				{},
				{},
				{}
			]
		}
	],
	"count": 3001,
	"totalTime": 236893,
	"collection": {
		"requests": [
			{
				"id": "00c8ab54-2434-4472-83a9-6fb6e81957ec",
				"method": "GET"
			}
		]
	}
}